{
  "𝟘": "0",
  "0⃣": "0",
  "0️⃣": "0",
  "⁰": "0",
  "⓪": "0",
  "【0】": "0",
  "『0』": "0",
  "≋0": "0",
  "░0": "0",
  "0̾": "0",
  "0̽": "0",
  "𝟙": "1",
  "1⃣": "1",
  "1️⃣": "1",
  "¹": "1",
  "①": "1",
  "【1】": "1",
  "『1』": "1",
  "≋1": "1",
  "░1": "1",
  "1̾": "1",
  "1̽": "1",
  "𝟚": "2",
  "2⃣": "2",
  "2️⃣": "2",
  "²": "2",
  "②": "2",
  "【2】": "2",
  "『2』": "2",
  "≋2": "2",
  "░2": "2",
  "2̾": "2",
  "2̽": "2",
  "𝟛": "3",
  "3⃣": "3",
  "3️⃣": "3",
  "³": "3",
  "③": "3",
  "【3】": "3",
  "『3』": "3",
  "≋3": "3",
  "░3": "3",
  "3̾": "3",
  "3̽": "3",
  "𝟜": "4",
  "4⃣": "4",
  "4️⃣": "4",
  "⁴": "4",
  "④": "4",
  "【4】": "4",
  "『4』": "4",
  "≋4": "4",
  "░4": "4",
  "4̾": "4",
  "4̽": "4",
  "𝟝": "5",
  "5⃣": "5",
  "5️⃣": "5",
  "⁵": "5",
  "⑤": "5",
  "【5】": "5",
  "『5』": "5",
  "≋5": "5",
  "░5": "5",
  "5̾": "5",
  "5̽": "5",
  "𝟞": "6",
  "6⃣": "6",
  "6️⃣": "6",
  "⁶": "6",
  "⑥": "6",
  "【6】": "6",
  "『6』": "6",
  "≋6": "6",
  "░6": "6",
  "6̾": "6",
  "6̽": "6",
  "𝟟": "7",
  "7⃣": "7",
  "7️⃣": "7",
  "⁷": "7",
  "⑦": "7",
  "【7】": "7",
  "『7』": "7",
  "≋7": "7",
  "░7": "7",
  "7̾": "7",
  "7̽": "7",
  "𝟠": "8",
  "8⃣": "8",
  "8️⃣": "8",
  "⁸": "8",
  "⑧": "8",
  "【8】": "8",
  "『8』": "8",
  "≋8": "8",
  "░8": "8",
  "8̾": "8",
  "8̽": "8",
  "𝟡": "9",
  "9⃣": "9",
  "9️⃣": "9",
  "⁹": "9",
  "⑨": "9",
  "【9】": "9",
  "『9』": "9",
  "≋9": "9",
  "░9": "9",
  "9̾": "9",
  "9̽": "9",
  "𝕒": "a",
  "ａ": "a",
  "ᴀ": "a",
  "🄰": "a",
  "🅰": "a",
  "ⓐ": "a",
  "𝙖": "a",
  "𝐚": "a",
  "𝗮": "a",
  "【a】": "a",
  "『a』": "a",
  "𝕓": "b",
  "ｂ": "b",
  "ʙ": "b",
  "🄱": "b",
  "🅱": "b",
  "ⓑ": "b",
  "𝙗": "b",
  "𝐛": "b",
  "𝗯": "b",
  "【b】": "b",
  "『b』": "b",
  "𝕔": "c",
  "ｃ": "c",
  "ᴄ": "c",
  "🄲": "c",
  "🅲": "c",
  "ⓒ": "c",
  "𝙘": "c",
  "𝐜": "c",
  "𝗰": "c",
  "【c】": "c",
  "『c』": "c",
  "𝕕": "d",
  "ｄ": "d",
  "ᴅ": "d",
  "🄳": "d",
  "🅳": "d",
  "ⓓ": "d",
  "𝙙": "d",
  "𝐝": "d",
  "𝗱": "d",
  "【d】": "d",
  "『d』": "d",
  "𝕖": "e",
  "ｅ": "e",
  "ᴇ": "e",
  "🄴": "e",
  "🅴": "e",
  "ⓔ": "e",
  "𝙚": "e",
  "𝐞": "e",
  "𝗲": "e",
  "【e】": "e",
  "『e』": "e",
  "𝕗": "f",
  "ｆ": "f",
  "ꜰ": "f",
  "🄵": "f",
  "🅵": "f",
  "ⓕ": "f",
  "𝙛": "f",
  "𝐟": "f",
  "𝗳": "f",
  "【f】": "f",
  "『f』": "f",
  "𝕘": "g",
  "ｇ": "g",
  "ɢ": "g",
  "🄶": "g",
  "🅶": "g",
  "ⓖ": "g",
  "𝙜": "g",
  "𝐠": "g",
  "𝗴": "g",
  "【g】": "g",
  "『g』": "g",
  "𝕙": "h",
  "ｈ": "h",
  "ʜ": "h",
  "🄷": "h",
  "🅷": "h",
  "ⓗ": "h",
  "𝙝": "h",
  "𝐡": "h",
  "𝗵": "h",
  "【h】": "h",
  "『h』": "h",
  "𝕚": "i",
  "ｉ": "i",
  "ɪ": "i",
  "🄸": "i",
  "🅸": "i",
  "ⓘ": "i",
  "𝙞": "i",
  "𝐢": "i",
  "𝗶": "i",
  "【i】": "i",
  "『i』": "i",
  "𝕛": "j",
  "ｊ": "j",
  "ᴊ": "j",
  "🄹": "j",
  "🅹": "j",
  "ⓙ": "j",
  "𝙟": "j",
  "𝐣": "j",
  "𝗷": "j",
  "【j】": "j",
  "『j』": "j",
  "𝕜": "k",
  "ｋ": "k",
  "ᴋ": "k",
  "🄺": "k",
  "🅺": "k",
  "ⓚ": "k",
  "𝙠": "k",
  "𝐤": "k",
  "𝗸": "k",
  "【k】": "k",
  "『k』": "k",
  "𝕝": "l",
  "ｌ": "l",
  "ʟ": "l",
  "🄻": "l",
  "🅻": "l",
  "ⓛ": "l",
  "𝙡": "l",
  "𝐥": "l",
  "𝗹": "l",
  "【l】": "l",
  "『l』": "l",
  "𝕞": "m",
  "ｍ": "m",
  "ᴍ": "m",
  "🄼": "m",
  "🅼": "m",
  "ⓜ": "m",
  "𝙢": "m",
  "𝐦": "m",
  "𝗺": "m",
  "【m】": "m",
  "『m』": "m",
  "𝕟": "n",
  "ｎ": "n",
  "ɴ": "n",
  "🄽": "n",
  "🅽": "n",
  "ⓝ": "n",
  "𝙣": "n",
  "𝐧": "n",
  "𝗻": "n",
  "【n】": "n",
  "『n』": "n",
  "𝕠": "o",
  "ｏ": "o",
  "ᴏ": "o",
  "🄾": "o",
  "🅾": "o",
  "ⓞ": "o",
  "𝙤": "o",
  "𝐨": "o",
  "𝗼": "o",
  "【o】": "o",
  "『o』": "o",
  "𝕡": "p",
  "ｐ": "p",
  "ᴘ": "p",
  "🄿": "p",
  "🅿": "p",
  "ⓟ": "p",
  "𝙥": "p",
  "𝐩": "p",
  "𝗽": "p",
  "【p】": "p",
  "『p』": "p",
  "𝕢": "q",
  "ｑ": "q",
  "Q": "q",
  "🅀": "q",
  "ⓠ": "q",
  "𝙦": "q",
  "𝐪": "q",
  "𝗾": "q",
  "【q】": "q",
  "『q』": "q",
  "𝕣": "r",
  "ｒ": "r",
  "ʀ": "r",
  "🅁": "r",
  "ⓡ": "r",
  "𝙧": "r",
  "𝐫": "r",
  "𝗿": "r",
  "【r】": "r",
  "『r』": "r",
  "𝕤": "s",
  "ｓ": "s",
  "ꜱ": "s",
  "🅂": "s",
  "ⓢ": "s",
  "𝙨": "s",
  "𝐬": "s",
  "𝘀": "s",
  "【s】": "s",
  "『s』": "s",
  "𝕥": "t",
  "ｔ": "t",
  "ᴛ": "t",
  "🅃": "t",
  "ⓣ": "t",
  "𝙩": "t",
  "𝐭": "t",
  "𝘁": "t",
  "【t】": "t",
  "『t』": "t",
  "𝕦": "u",
  "ｕ": "u",
  "ᴜ": "u",
  "🅄": "u",
  "ⓤ": "u",
  "𝙪": "u",
  "𝐮": "u",
  "𝘂": "u",
  "【u】": "u",
  "『u』": "u",
  "𝕧": "v",
  "ｖ": "v",
  "ᴠ": "v",
  "🅅": "v",
  "ⓥ": "v",
  "𝙫": "v",
  "𝐯": "v",
  "𝘃": "v",
  "【v】": "v",
  "『v』": "v",
  "𝕨": "w",
  "ｗ": "w",
  "ᴡ": "w",
  "🅆": "w",
  "ⓦ": "w",
  "𝙬": "w",
  "𝐰": "w",
  "𝘄": "w",
  "【w】": "w",
  "『w』": "w",
  "𝕩": "x",
  "ｘ": "x",
  "x": "x",
  "🅇": "x",
  "ⓧ": "x",
  "𝙭": "x",
  "𝐱": "x",
  "𝘅": "x",
  "【x】": "x",
  "『x』": "x",
  "𝕪": "y",
  "ｙ": "y",
  "ʏ": "y",
  "🅈": "y",
  "ⓨ": "y",
  "𝙮": "y",
  "𝐲": "y",
  "𝘆": "y",
  "【y】": "y",
  "『y』": "y",
  "𝕫": "z",
  "ｚ": "z",
  "ᴢ": "z",
  "🅉": "z",
  "ⓩ": "z",
  "𝙯": "z",
  "𝐳": "z",
  "𝘇": "z",
  "【z】": "z",
  "『z』": "z"
}